tg_util/__init__.py
tg_util/downloader.py
tg_util/exporter.py
tg_util/src/__init__.py
tg_util/src/input.py
tg_util/src/log.py
tg_util/src/sheet.py
tg_util/src/arc/__init__.py
tg_util/src/arc/base.py
tg_util/src/arc/factory.py
tg_util/src/arc/mysqlx.py
tg_util/src/arc/pg.py
tg_util/src/arc/sqlite.py
tg_util/src/tg/utils.py
tg_util/src/tg/utils.pyi
tg_util/src/tg/messages/element.py
tg_util/src/tg/messages/export.py
tg_util/src/tg/messages/wrapper.py
tg_util/src/tg/sessions/__init__.py
tg_util/src/tg/sessions/custom.py
tg_util/src/tg/sessions/factory.py
tg_util/src/tg/sessions/mysqlx.py
tg_util/src/tg/sessions/pg.py
tg_util/src/types/__init__.py
tg_util/src/types/_abc.py
tg_util/src/types/enums.py
tg_util/src/types/errors.py
tg_util/src/types/structs.py
tg_util/src/types/tqdm.py
tg_util/src/types/tqdm.pyi
tg_util/src/utils/__init__.py
tg_util/src/utils/aiohelper.py
tg_util/src/utils/helper.py
tg_util-0.1.17.dist-info/METADATA
tg_util-0.1.17.dist-info/WHEEL
tg_util-0.1.17.dist-info/entry_points.txt
tg_util-0.1.17.dist-info/licenses/LICENSE
tg_util-0.1.17.dist-info/RECORD
