Metadata-Version: 2.4
Name: tg-util
Version: 0.1.17
Summary: telegram utilities for personal use case
Project-URL: Repository, https://github.com/unhealme/tg-util
Maintainer-email: unhealme <o2tongpethuk@gmail.com>
License-File: LICENSE
Requires-Python: >=3.12
Requires-Dist: aiofiles>=24.1.0
Requires-Dist: msgspec[yaml]>=0.19.0
Requires-Dist: pillow>=11.2.1
Requires-Dist: python-socks[asyncio]>=2.7.1
Requires-Dist: tabulate>=0.9.0
Requires-Dist: telethon[cryptg]>=1.40.0
Requires-Dist: tqdm>=4.67.1
Provides-Extra: mysql
Requires-Dist: mysqlx-connector-python>=9.3.0; extra == 'mysql'
Provides-Extra: perf
Requires-Dist: uvloop>=0.21.0; extra == 'perf'
Provides-Extra: pg
Requires-Dist: asyncpg>=0.30.0; extra == 'pg'
